[
  {
    "skill_id": "1",
    "name": "Python",
    "category": "Programming Language",
    "description": "General-purpose programming language.",
    "related_skills": [
      "Django",
      "Flask",
      "Pandas"
    ],
    "source": "Standard",
    "updated_at": "2025-04-16T21:09:16.178733"
  },
  {
    "skill_id": "2",
    "name": "JavaScript",
    "category": "Programming Language",
    "description": "Scripting language for web development.",
    "related_skills": [
      "React",
      "Node.js",
      "Vue.js"
    ],
    "source": "Standard",
    "updated_at": "2025-04-16T21:09:16.250345"
  },
  {
    "skill_id": "3",
    "name": "SQL",
    "category": "Database",
    "description": "Language for querying databases.",
    "related_skills": [
      "PostgreSQL",
      "MySQL",
      "SQLite"
    ],
    "source": "Standard",
    "updated_at": "2025-04-16T21:09:16.252006"
  },
  {
    "skill_id": "4",
    "name": "Machine Learning",
    "category": "AI/ML",
    "description": "Techniques for building predictive models.",
    "related_skills": [
      "scikit-learn",
      "TensorFlow",
      "PyTorch"
    ],
    "source": "Standard",
    "updated_at": "2025-04-16T21:09:16.252578"
  },
  {
    "skill_id": "5",
    "name": "Data Analysis",
    "category": "Data Science",
    "description": "Techniques for analyzing data.",
    "related_skills": [
      "Pandas",
      "NumPy",
      "Excel"
    ],
    "source": "Standard",
    "updated_at": "2025-04-16T21:09:16.253041"
  },
  {
    "skill_id": "6",
    "name": "Project Management",
    "category": "Management",
    "description": "Managing projects and teams.",
    "related_skills": [
      "Agile",
      "Scrum",
      "Kanban"
    ],
    "source": "Standard",
    "updated_at": "2025-04-16T21:09:16.253475"
  },
  {
    "skill_id": "7",
    "name": "Communication",
    "category": "Soft Skill",
    "description": "Effective verbal and written communication.",
    "related_skills": [],
    "source": "Standard",
    "updated_at": "2025-04-16T21:09:16.253881"
  },
  {
    "skill_id": "8",
    "name": "Problem Solving",
    "category": "Soft Skill",
    "description": "Approaching and resolving issues.",
    "related_skills": [],
    "source": "Standard",
    "updated_at": "2025-04-16T21:09:16.254277"
  },
  {
    "skill_id": "9",
    "name": "Leadership",
    "category": "Soft Skill",
    "description": "Leading teams and projects.",
    "related_skills": [],
    "source": "Standard",
    "updated_at": "2025-04-16T21:09:16.254668"
  },
  {
    "skill_id": "10",
    "name": "Cloud Computing",
    "category": "IT",
    "description": "Using remote servers for computation/storage.",
    "related_skills": [
      "AWS",
      "Azure",
      "GCP"
    ],
    "source": "Standard",
    "updated_at": "2025-04-16T21:09:16.255051"
  },
  {
    "skill_id": "11",
    "name": "DevOps",
    "category": "IT",
    "description": "Practices for automating IT operations.",
    "related_skills": [
      "CI/CD",
      "Docker",
      "Kubernetes"
    ],
    "source": "Standard",
    "updated_at": "2025-04-16T21:09:16.255456"
  },
  {
    "skill_id": "12",
    "name": "Cybersecurity",
    "category": "IT",
    "description": "Protecting systems and data from threats.",
    "related_skills": [
      "Network Security",
      "Encryption"
    ],
    "source": "Standard",
    "updated_at": "2025-04-16T21:09:16.255878"
  },
  {
    "skill_id": "13",
    "name": "HTML",
    "category": "Web Development",
    "description": "Markup language for web pages.",
    "related_skills": [
      "CSS",
      "JavaScript"
    ],
    "source": "Standard",
    "updated_at": "2025-04-16T21:09:16.256280"
  },
  {
    "skill_id": "14",
    "name": "CSS",
    "category": "Web Development",
    "description": "Styling language for web pages.",
    "related_skills": [
      "HTML",
      "JavaScript"
    ],
    "source": "Standard",
    "updated_at": "2025-04-16T21:09:16.256680"
  },
  {
    "skill_id": "15",
    "name": "Time Management",
    "category": "Soft Skill",
    "description": "Efficient use of time and prioritization.",
    "related_skills": [],
    "source": "Standard",
    "updated_at": "2025-04-16T21:09:16.257063"
  },
  {
    "skill_id": "16",
    "name": "Critical Thinking",
    "category": "Soft Skill",
    "description": "Objective analysis and evaluation.",
    "related_skills": [],
    "source": "Standard",
    "updated_at": "2025-04-16T21:09:16.257453"
  },
  {
    "skill_id": "17",
    "name": "Customer Service",
    "category": "Business",
    "description": "Assisting and serving customers.",
    "related_skills": [],
    "source": "Standard",
    "updated_at": "2025-04-16T21:09:16.257825"
  },
  {
    "skill_id": "18",
    "name": "Financial Analysis",
    "category": "Business",
    "description": "Analyzing financial data.",
    "related_skills": [
      "Excel",
      "Accounting"
    ],
    "source": "Standard",
    "updated_at": "2025-04-16T21:09:16.258235"
  },
  {
    "skill_id": "19",
    "name": "Marketing",
    "category": "Business",
    "description": "Promoting products and services.",
    "related_skills": [
      "SEO",
      "Content Marketing"
    ],
    "source": "Standard",
    "updated_at": "2025-04-16T21:09:16.258652"
  },
  {
    "skill_id": "20",
    "name": "Research",
    "category": "Academic",
    "description": "Systematic investigation and study.",
    "related_skills": [],
    "source": "Standard",
    "updated_at": "2025-04-16T21:09:16.259053"
  }
]